[
  {
    "platform": "GOG",
    "lastPlayed": "2019-01-01",
    "hoursPlayed": 3,
    "id": 1441269533,
    "url": "https://gogdb.org/product/1441269533",
    "game": "80 Days"
  },
  {
    "platform": "GOG",
    "lastPlayed": "2021-06-21",
    "hoursPlayed": 10,
    "id": 1207662903,
    "url": "https://gogdb.org/product/1207662903",
    "game": "Blackwell Convergence"
  },
  {
    "platform": "GOG",
    "lastPlayed": "2021-07-01",
    "hoursPlayed": 12,
    "id": 1207662913,
    "url": "https://gogdb.org/product/1207662913",
    "game": "Blackwell Deception"
  },
  {
    "platform": "GOG",
    "lastPlayed": "2021-06-01",
    "hoursPlayed": 8,
    "id": 1207662883,
    "url": "https://gogdb.org/product/1207662883",
    "game": "Blackwell Legacy"
  },
  {
    "platform": "GOG",
    "lastPlayed": "2021-06-11",
    "hoursPlayed": 10,
    "id": 1207662893,
    "url": "https://gogdb.org/product/1207662893",
    "game": "Blackwell Unbound"
  },
  {
    "platform": "GOG",
    "lastPlayed": "2023-08-01",
    "hoursPlayed": 16,
    "id": 1456702644,
    "url": "https://gogdb.org/product/1456702644",
    "game": "Cultist Simulator"
  },
  {
    "platform": "GOG",
    "lastPlayed": "2017-08-01",
    "hoursPlayed": 22,
    "id": 1207666503,
    "url": "https://gogdb.org/product/1207666503",
    "game": "Dreamfall Chapters: The Final Cut"
  },
  {
    "platform": "GOG",
    "lastPlayed": "2018-01-01",
    "hoursPlayed": 22,
    "id": 1207659045,
    "url": "https://gogdb.org/product/1207659045",
    "game": "Dreamfall: The Longest Journey"
  },
  {
    "platform": "GOG",
    "lastPlayed": "2018-12-31",
    "hoursPlayed": 12,
    "id": 1648559910,
    "url": "https://gogdb.org/product/1648559910",
    "game": "Frostpunk"
  },
  {
    "platform": "GOG",
    "lastPlayed": "2015-01-01",
    "hoursPlayed": 6,
    "id": 1207659073,
    "url": "https://gogdb.org/product/1207659073",
    "game": "Gemini Rue"
  },
  {
    "platform": "GOG",
    "lastPlayed": "2018-02-01",
    "hoursPlayed": 12,
    "id": 1207667183,
    "url": "https://gogdb.org/product/1207667183",
    "game": "Grim Fandango Remastered"
  },
  {
    "platform": "GOG",
    "lastPlayed": "2015-01-01",
    "hoursPlayed": 2,
    "id": 1207665623,
    "url": "https://gogdb.org/product/1207665623",
    "game": "Hatoful Boyfriend"
  },
  {
    "platform": "GOG",
    "lastPlayed": "2014-01-01",
    "hoursPlayed": 1,
    "id": 1207659593,
    "url": "https://gogdb.org/product/1207659593",
    "game": "I Have No Mouth And I Must Scream"
  },
  {
    "platform": "GOG",
    "lastPlayed": "2017-12-01",
    "hoursPlayed": 5,
    "id": 1916896012,
    "url": "https://gogdb.org/product/1916896012",
    "game": "INSIDE"
  },
  {
    "platform": "GOG",
    "lastPlayed": "2019-03-01",
    "hoursPlayed": 7,
    "id": 1460710709,
    "url": "https://gogdb.org/product/1460710709",
    "game": "Kathy Rain"
  },
  {
    "platform": "GOG",
    "lastPlayed": "2012-01-01",
    "hoursPlayed": 50,
    "id": 1207658890,
    "url": "https://gogdb.org/product/1207658890",
    "game": "Neverwinter Nights Diamond"
  },
  {
    "platform": "GOG",
    "lastPlayed": "2014-01-01",
    "hoursPlayed": 3,
    "id": 1207659209,
    "url": "https://gogdb.org/product/1207659209",
    "game": "Papers, Please"
  },
  {
    "platform": "GOG",
    "lastPlayed": "2017-12-01",
    "hoursPlayed": 20,
    "id": 1207666813,
    "url": "https://gogdb.org/product/1207666813",
    "game": "Pillars of Eternity"
  },
  {
    "platform": "GOG",
    "lastPlayed": "2016-01-01",
    "hoursPlayed": 6,
    "id": 1207658887,
    "url": "https://gogdb.org/product/1207658887",
    "game": "Planescape: Torment"
  },
  {
    "platform": "GOG",
    "lastPlayed": "2018-01-01",
    "hoursPlayed": 10,
    "id": 1207659144,
    "url": "https://gogdb.org/product/1207659144",
    "game": "Primordia"
  },
  {
    "platform": "GOG",
    "lastPlayed": "2013-06-01",
    "hoursPlayed": 6,
    "id": 1207659043,
    "url": "https://gogdb.org/product/1207659043",
    "game": "Resonance"
  },
  {
    "platform": "GOG",
    "lastPlayed": "2013-01-01",
    "hoursPlayed": 25,
    "id": 1430740458,
    "url": "https://gogdb.org/product/1430740458",
    "game": "Saints Row 2"
  },
  {
    "platform": "GOG",
    "lastPlayed": "2018-07-01",
    "hoursPlayed": "8",
    "id": 1454499527,
    "url": "https://gogdb.org/product/1454499527",
    "game": "Shardlight"
  },
  {
    "platform": "GOG",
    "lastPlayed": "2016-01-01",
    "hoursPlayed": 10,
    "id": 1207658848,
    "url": "https://gogdb.org/product/1207658848",
    "game": "Syberia"
  },
  {
    "platform": "GOG",
    "lastPlayed": "2016-07-01",
    "hoursPlayed": 12,
    "id": 1430234218,
    "url": "https://gogdb.org/product/1430234218",
    "game": "Technobabylon"
  },
  {
    "platform": "GOG",
    "lastPlayed": "2013-01-01",
    "hoursPlayed": 45,
    "id": 1207658794,
    "url": "https://gogdb.org/product/1207658794",
    "game": "The Longest Journey"
  },
  {
    "platform": "GOG",
    "lastPlayed": "2014-04-01",
    "hoursPlayed": 3,
    "id": 1207660263,
    "url": "https://gogdb.org/product/1207660263",
    "game": "The Shivah"
  },
  {
    "platform": "GOG",
    "lastPlayed": "2012-01-01",
    "hoursPlayed": 25,
    "id": 1207658889,
    "url": "https://gogdb.org/product/1207658889",
    "game": "The Temple of Elemental Evil"
  },
  {
    "platform": "GOG",
    "lastPlayed": "2018-01-01",
    "hoursPlayed": 6,
    "id": 1207659072,
    "url": "https://gogdb.org/product/1207659072",
    "game": "To The Moon"
  },
  {
    "platform": "GOG",
    "lastPlayed": "2018-04-01",
    "hoursPlayed": 6,
    "id": 1429612159,
    "url": "https://gogdb.org/product/1429612159",
    "game": "Transistor"
  },
  {
    "platform": "GOG",
    "lastPlayed": "2019-02-01",
    "hoursPlayed": 12,
    "id": 1266051739,
    "url": "https://gogdb.org/product/1266051739",
    "game": "Tyranny"
  },
  {
    "platform": "GOG",
    "lastPlayed": "2019-01-01",
    "hoursPlayed": 12,
    "id": 1637485057,
    "url": "https://gogdb.org/product/1637485057",
    "game": "Unavowed"
  }
]